pollination/dragonfly_annual_energy_use/__init__.py
pollination/dragonfly_annual_energy_use/entry.py
pollination_dragonfly_annual_energy_use-0.3.6.dist-info/LICENSE
pollination_dragonfly_annual_energy_use-0.3.6.dist-info/METADATA
pollination_dragonfly_annual_energy_use-0.3.6.dist-info/WHEEL
pollination_dragonfly_annual_energy_use-0.3.6.dist-info/top_level.txt
pollination_dragonfly_annual_energy_use-0.3.6.dist-info/RECORD
