Metadata-Version: 2.1
Name: pollination-dragonfly-annual-energy-use
Version: 0.3.6
Summary: Run an annual energy simulation for a Dragonfly Model and compute energy use intensity.
Home-page: https://github.com/pollination/dragonfly-annual-energy-use
Author: ladybug-tools
Author-email: info@ladybug.tools
Maintainer: chris, ladybug-tools
Maintainer-email: chris@ladybug.tools, info@ladybug.tools
License: PolyForm Shield License 1.0.0, https://polyformproject.org/wp-content/uploads/2020/06/PolyForm-Shield-1.0.0.txt
Project-URL: icon, https://raw.githubusercontent.com/ladybug-tools/artwork/master/icons_components/dragonfly/png/dfeui.png
Project-URL: docker, https://hub.docker.com/r/ladybugtools/dragonfly-energy
Keywords: dragonfly,energy,ladybug-tools,energyplus,openstudio,energy,dragonfly-annual-energy-use
License-File: LICENSE
Requires-Dist: pollination-honeybee-energy>=0.7.13
Requires-Dist: pollination-dragonfly-energy>=0.2.8
Requires-Dist: pollination-alias>=0.11.4
